odoo/addons/l10n_it_fatturapa_out_oss/README.rst
odoo/addons/l10n_it_fatturapa_out_oss/__init__.py
odoo/addons/l10n_it_fatturapa_out_oss/__manifest__.py
odoo/addons/l10n_it_fatturapa_out_oss/i18n/it.po
odoo/addons/l10n_it_fatturapa_out_oss/i18n/l10n_it_fatturapa_out_oss.pot
odoo/addons/l10n_it_fatturapa_out_oss/readme/CONTRIBUTORS.rst
odoo/addons/l10n_it_fatturapa_out_oss/readme/DESCRIPTION.rst
odoo/addons/l10n_it_fatturapa_out_oss/static/description/icon.png
odoo/addons/l10n_it_fatturapa_out_oss/static/description/index.html
odoo/addons/l10n_it_fatturapa_out_oss/tests/__init__.py
odoo/addons/l10n_it_fatturapa_out_oss/tests/test_fatturapa_xml_validation.py
odoo/addons/l10n_it_fatturapa_out_oss/tests/data/IT06363391001_00001.xml
odoo/addons/l10n_it_fatturapa_out_oss/tests/data/IT06363391001_00002.xml
odoo/addons/l10n_it_fatturapa_out_oss/wizard/__init__.py
odoo/addons/l10n_it_fatturapa_out_oss/wizard/l10n_eu_oss_wizard.py
odoo/addons/l10n_it_fatturapa_out_oss/wizard/wizard_export_fatturapa.py
odoo12_addon_l10n_it_fatturapa_out_oss-12.0.1.0.0.99.dev8.dist-info/METADATA
odoo12_addon_l10n_it_fatturapa_out_oss-12.0.1.0.0.99.dev8.dist-info/WHEEL
odoo12_addon_l10n_it_fatturapa_out_oss-12.0.1.0.0.99.dev8.dist-info/top_level.txt
odoo12_addon_l10n_it_fatturapa_out_oss-12.0.1.0.0.99.dev8.dist-info/RECORD
