Metadata-Version: 2.1
Name: odoo12-addon-l10n_it_fatturapa_out_oss
Version: 12.0.1.0.0.99.dev8
Summary: OSS in fatturapa
Home-page: https://github.com/OCA/l10n-italy
Author: Sergio Corato,Odoo Community Association (OCA)
Author-email: support@odoo-community.org
License: AGPL-3
Classifier: Programming Language :: Python
Classifier: Framework :: Odoo
Classifier: Framework :: Odoo :: 12.0
Classifier: License :: OSI Approved :: GNU Affero General Public License v3
Classifier: Development Status :: 3 - Alpha
Requires-Python: >=3.5
Requires-Dist: odoo12-addon-l10n-eu-oss
Requires-Dist: odoo12-addon-l10n-it-fatturapa-out
Requires-Dist: odoo<12.1dev,>=12.0a
